fallom/__init__.py
fallom/models.py
fallom/prompts.py
fallom/evals/__init__.py
fallom/evals/core.py
fallom/evals/helpers.py
fallom/evals/prompts.py
fallom/evals/types.py
fallom/trace/__init__.py
fallom/trace/core.py
fallom/trace/session.py
fallom/trace/types.py
fallom/trace/utils.py
fallom/trace/wrappers/__init__.py
fallom/trace/wrappers/anthropic.py
fallom/trace/wrappers/google_ai.py
fallom/trace/wrappers/langchain.py
fallom/trace/wrappers/openai.py
fallom-0.2.7.dist-info/METADATA
fallom-0.2.7.dist-info/WHEEL
fallom-0.2.7.dist-info/top_level.txt
fallom-0.2.7.dist-info/RECORD
