Metadata-Version: 2.4
Name: fallom
Version: 0.2.7
Summary: Model A/B testing, prompt management, and tracing for LLM applications
Author-email: Fallom <hello@fallom.com>
License: MIT
Project-URL: Homepage, https://fallom.com
Project-URL: Documentation, https://docs.fallom.com
Project-URL: App, https://app.fallom.com
Project-URL: Repository, https://github.com/Fallomai/fallom-python-sdk
Keywords: llm,tracing,a/b testing,opentelemetry,ai,ml
Classifier: Development Status :: 3 - Alpha
Classifier: Intended Audience :: Developers
Classifier: License :: OSI Approved :: MIT License
Classifier: Programming Language :: Python :: 3
Classifier: Programming Language :: Python :: 3.9
Classifier: Programming Language :: Python :: 3.10
Classifier: Programming Language :: Python :: 3.11
Classifier: Programming Language :: Python :: 3.12
Classifier: Topic :: Software Development :: Libraries :: Python Modules
Classifier: Topic :: Scientific/Engineering :: Artificial Intelligence
Requires-Python: >=3.9
Requires-Dist: opentelemetry-api>=1.20.0
Requires-Dist: opentelemetry-sdk>=1.20.0
Requires-Dist: opentelemetry-exporter-otlp-proto-http>=1.20.0
Requires-Dist: requests>=2.28.0
Provides-Extra: openai
Requires-Dist: opentelemetry-instrumentation-openai>=0.1.0; extra == "openai"
Provides-Extra: anthropic
Requires-Dist: opentelemetry-instrumentation-anthropic>=0.1.0; extra == "anthropic"
Provides-Extra: langchain
Requires-Dist: langchain-core>=0.1.0; extra == "langchain"
Provides-Extra: all
Requires-Dist: opentelemetry-instrumentation-openai>=0.1.0; extra == "all"
Requires-Dist: opentelemetry-instrumentation-anthropic>=0.1.0; extra == "all"
Requires-Dist: langchain-core>=0.1.0; extra == "all"
Provides-Extra: dev
Requires-Dist: pytest>=7.0.0; extra == "dev"
Requires-Dist: pytest-asyncio>=0.21.0; extra == "dev"
